pisces/__init__.py
pisces/client.py
pisces/crud.py
pisces/request.py
pisces/util.py
pisces/commands/__init__.py
pisces/commands/create.py
pisces/commands/db2db.py
pisces/commands/drop.py
pisces/commands/main.py
pisces/commands/sac2db.py
pisces/io/__init__.py
pisces/io/flatfile.py
pisces/io/mseed.py
pisces/io/readwaveform.py
pisces/io/sac.py
pisces/io/trace.py
pisces/io/util.py
pisces/io/lib/libconvert.so
pisces/io/lib/libecompression.so
pisces/schema/__init__.py
pisces/schema/css3.py
pisces/schema/kbcore.py
pisces/schema/util.py
pisces/tables/__init__.py
pisces/tables/css3.py
pisces/tables/kbcore.py
pisces_db-0.2.3.dist-info/DESCRIPTION.rst
pisces_db-0.2.3.dist-info/METADATA
pisces_db-0.2.3.dist-info/RECORD
pisces_db-0.2.3.dist-info/WHEEL
pisces_db-0.2.3.dist-info/entry_points.txt
pisces_db-0.2.3.dist-info/metadata.json
pisces_db-0.2.3.dist-info/pbr.json
pisces_db-0.2.3.dist-info/top_level.txt
