Metadata-Version: 2.0
Name: pisces-db
Version: 0.2.3
Summary: A Practical Seismological Database Library in Python.
Home-page: https://github.com/jkmacc-LANL/pisces
Author: Jonathan MacCarthy
Author-email: jkmacc@lanl.gov
License: LANL-MIT
Download-URL: https://github.com/jkmacc-LANL/pisces/tarball/0.2.1
Keywords: seismology,geophysics,database
Platform: Mac OS X
Platform: Linux/Unix
Classifier: Development Status :: 3 - Alpha
Classifier: Environment :: Console
Classifier: Intended Audience :: Science/Research
Classifier: Intended Audience :: Developers
Classifier: License :: OSI Approved :: MIT License
Classifier: Operating System :: OS Independent
Classifier: Programming Language :: Python :: 2
Classifier: Programming Language :: Python :: 2.7
Classifier: Topic :: Scientific/Engineering
Classifier: Topic :: Database
Classifier: Topic :: Scientific/Engineering :: Physics
Requires-Dist: Click
Requires-Dist: numpy
Requires-Dist: obspy (>=1.0)
Requires-Dist: sqlalchemy (>=0.9)
